pytest_smart_rerun.py
smart_rerun_report.py
pytest_smart_rerun-0.1.3.dist-info/licenses/LICENSE
pytest_smart_rerun-0.1.3.dist-info/METADATA
pytest_smart_rerun-0.1.3.dist-info/WHEEL
pytest_smart_rerun-0.1.3.dist-info/entry_points.txt
pytest_smart_rerun-0.1.3.dist-info/top_level.txt
pytest_smart_rerun-0.1.3.dist-info/RECORD
