Metadata-Version: 2.4
Name: pytest-smart-rerun
Version: 0.1.3
Summary: A Pytest plugin for intelligent retrying of flaky tests.
Home-page: https://github.com/Aki-07/pytest-smart-rerun
Author: Akilesh KR
Author-email: akileshramesh2003@gmail.com
License: MIT
Project-URL: Documentation, https://github.com/Aki-07/pytest-smart-rerun#readme
Project-URL: Issues, https://github.com/Aki-07/pytest-smart-rerun/issues
Classifier: Development Status :: 3 - Alpha
Classifier: Framework :: Pytest
Classifier: Intended Audience :: Developers
Classifier: License :: OSI Approved :: MIT License
Classifier: Programming Language :: Python
Classifier: Programming Language :: Python :: 3
Classifier: Programming Language :: Python :: 3.8
Classifier: Programming Language :: Python :: 3.9
Classifier: Programming Language :: Python :: 3.10
Classifier: Programming Language :: Python :: 3.11
Classifier: Programming Language :: Python :: 3.12
Classifier: Topic :: Software Development :: Testing
Requires-Python: >=3.8
License-File: LICENSE
Dynamic: author
Dynamic: author-email
Dynamic: classifier
Dynamic: description
Dynamic: description-content-type
Dynamic: home-page
Dynamic: license
Dynamic: license-file
Dynamic: project-url
Dynamic: requires-python
Dynamic: summary
